nbastatpy/__init__.py
nbastatpy/config.py
nbastatpy/game.py
nbastatpy/player.py
nbastatpy/season.py
nbastatpy/standardize.py
nbastatpy/team.py
nbastatpy/utils.py
nbastatpy/validators.py
nbastatpy-0.2.0.dist-info/licenses/LICENSE
nbastatpy-0.2.0.dist-info/METADATA
nbastatpy-0.2.0.dist-info/WHEEL
nbastatpy-0.2.0.dist-info/top_level.txt
nbastatpy-0.2.0.dist-info/RECORD
