Metadata-Version: 2.4
Name: nbastatpy
Version: 0.2.0
Summary: An easy-to-use wrapper for nba_api to easily find data for a player, game, team, or season
Keywords: basketball,data,nba,sports,stats
Classifier: Intended Audience :: Science/Research
Classifier: License :: OSI Approved :: MIT License
Requires-Python: >=3.10
License-File: LICENSE
Requires-Dist: bs4>=0.0.2
Requires-Dist: loguru>=0.7.3
Requires-Dist: nba-api>=1.6.1
Requires-Dist: pandas>=2.2.3
Requires-Dist: pillow>=11.0.0
Requires-Dist: requests>=2.32.3
Requires-Dist: rich>=13.9.4
Dynamic: license-file
